CHANGES.rst
LICENSE
MANIFEST.in
README.rst
setup.py
src/inkpy/__init__.py
src/inkpy/api.py
src/inkpy/models.py
src/inkpy/utils.py
src/inkpy.egg-info/PKG-INFO
src/inkpy.egg-info/SOURCES.txt
src/inkpy.egg-info/dependency_links.txt
src/inkpy.egg-info/not-zip-safe
src/inkpy.egg-info/requires.txt
src/inkpy.egg-info/top_level.txt
src/inkpy/management/__init__.py
src/inkpy/management/commands/__init__.py
src/inkpy/management/commands/convert2pdf.py
src/inkpy/tests/__init__.py
src/inkpy/tests/__init__.pyc
src/inkpy/tests/settings.py
src/inkpy/tests/settings.pyc
src/inkpy/tests/tests.py