Metadata-Version: 1.1
Name: inkpy
Version: 0.1.0-alpha
Summary: InkPy - provide tool to fill Django style template in odt file
Home-page: https://github.com/quamilek/InkPy
Author: Kamil Warguła
Author-email: kwargula@gmail.com
License: Apache Software License v2.0
Platform: any
Classifier: Development Status :: 3 - Alpha
Classifier: Framework :: Django
Classifier: Intended Audience :: Developers
Classifier: Natural Language :: English
Classifier: License :: OSI Approved :: BSD License
Classifier: Operating System :: POSIX
Classifier: Programming Language :: Python
Classifier: Programming Language :: Python :: 2.7
